tempcache/__init__.py
tempcache/caching.py
tempcache-0.0.13.dist-info/WHEEL
tempcache-0.0.13.dist-info/METADATA
tempcache-0.0.13.dist-info/RECORD
