Metadata-Version: 2.4
Name: tempcache
Version: 0.0.13
Summary: Python library to cache data and function results in temporary files
Keywords: caching,tempfiles
Author: furechan
Author-email: furechan <furechan@xsmail.com>
License-Expression: MIT
Classifier: Programming Language :: Python :: 3
Classifier: License :: OSI Approved :: MIT License
Classifier: Operating System :: OS Independent
Requires-Python: >=3.10
Project-URL: homepage, https://github.com/furechan/tempcache
